fink_utils/__init__.py
fink_utils/tester.py
fink_utils/broker/__init__.py
fink_utils/broker/avroUtils.py
fink_utils/broker/distributionUtils.py
fink_utils/broker/sparkUtils.py
fink_utils/cutouts/__init__.py
fink_utils/cutouts/utils.py
fink_utils/data/__init__.py
fink_utils/data/utils.py
fink_utils/hbase/__init__.py
fink_utils/hbase/utils.py
fink_utils/hdfs/__init__.py
fink_utils/hdfs/utils.py
fink_utils/logging/__init__.py
fink_utils/logging/logs.py
fink_utils/photometry/__init__.py
fink_utils/photometry/conversion.py
fink_utils/photometry/test.py
fink_utils/photometry/utils.py
fink_utils/photometry/vect_conversion.py
fink_utils/science/__init__.py
fink_utils/science/utils.py
fink_utils/slack_bot/__init__.py
fink_utils/slack_bot/bot.py
fink_utils/slack_bot/bot_test.py
fink_utils/slack_bot/image.py
fink_utils/slack_bot/msg_builder.py
fink_utils/slack_bot/section.py
fink_utils/slack_bot/rich_text/__init__.py
fink_utils/slack_bot/rich_text/rich_list.py
fink_utils/slack_bot/rich_text/rich_preformatted.py
fink_utils/slack_bot/rich_text/rich_quote.py
fink_utils/slack_bot/rich_text/rich_section.py
fink_utils/slack_bot/rich_text/rich_text.py
fink_utils/slack_bot/rich_text/rich_text_element.py
fink_utils/spark/__init__.py
fink_utils/spark/partitioning.py
fink_utils/spark/schema_converter.py
fink_utils/spark/utils.py
fink_utils/sso/__init__.py
fink_utils/sso/ephem.py
fink_utils/sso/miriade.py
fink_utils/sso/periods.py
fink_utils/sso/spins.py
fink_utils/sso/ssoft.py
fink_utils/sso/utils.py
fink_utils/tg_bot/__init__.py
fink_utils/tg_bot/utils.py
fink_utils/xmatch/__init__.py
fink_utils/xmatch/otypes.txt
fink_utils/xmatch/simbad.py
fink_utils/xmatch/vsx.py
fink_utils-0.56.0.dist-info/LICENSE
fink_utils-0.56.0.dist-info/METADATA
fink_utils-0.56.0.dist-info/WHEEL
fink_utils-0.56.0.dist-info/top_level.txt
fink_utils-0.56.0.dist-info/RECORD
