Metadata-Version: 2.1
Name: fink_utils
Version: 0.56.0
Summary: Collection of useful functionalities used across the Fink ecosystem.
Home-page: https://github.com/astrolabsoftware/fink-utils
Author: JulienPeloton
Author-email: peloton@lal.in2p3.fr
Project-URL: Source, https://github.com/astrolabsoftware/fink-utils
Classifier: Programming Language :: Python :: 3.7
Classifier: License :: OSI Approved :: Apache Software License
Classifier: Operating System :: Unix
Classifier: Development Status :: 4 - Beta
Classifier: Intended Audience :: Science/Research
License-File: LICENSE
